python_sdb-0.1.dist-info/DESCRIPTION.rst
python_sdb-0.1.dist-info/METADATA
python_sdb-0.1.dist-info/RECORD
python_sdb-0.1.dist-info/WHEEL
python_sdb-0.1.dist-info/entry_points.txt
python_sdb-0.1.dist-info/metadata.json
python_sdb-0.1.dist-info/top_level.txt
scripts/__init__.py
scripts/sdb_dump_common.py
scripts/sdb_dump_database.py
scripts/sdb_dump_info.py
scripts/sdb_dump_patch.py
scripts/sdb_dump_raw.py
scripts/sdb_dump_shims.py
scripts/shims_hash_shims.py
sdb/__init__.py
sdb/patchbits.py
sdb/sdb.py
